src/__init__.py
src/cli.py
src/generator.py
src/parser.py
openapi_gen_wrapper-0.1.2.dist-info/LICENSE
openapi_gen_wrapper-0.1.2.dist-info/METADATA
openapi_gen_wrapper-0.1.2.dist-info/WHEEL
openapi_gen_wrapper-0.1.2.dist-info/entry_points.txt
openapi_gen_wrapper-0.1.2.dist-info/top_level.txt
openapi_gen_wrapper-0.1.2.dist-info/RECORD
