Metadata-Version: 2.1
Name: openapi-gen-wrapper
Version: 0.1.2
Summary: A Python tool for generating OpenAPI specs
Home-page: https://github.com/arkodeepsen/openapi-gen
Author: Arkodeep Sen
Author-email: arkodeepsen72@gmail.com.com
Classifier: Programming Language :: Python :: 3
Classifier: License :: OSI Approved :: MIT License
Classifier: Operating System :: OS Independent
License-File: LICENSE
Requires-Dist: click
Requires-Dist: pyyaml
